{"file:///e%3A/Praktikum/API%20Anwendung/jss/filters.js":{"language":"JavaScript","code":47,"comment":1,"blank":10},"file:///e%3A/Praktikum/API%20Anwendung/jss/classes.js":{"language":"JavaScript","code":129,"comment":9,"blank":10},"file:///e%3A/Praktikum/API%20Anwendung/jss/main.js":{"language":"JavaScript","code":205,"comment":50,"blank":38},"file:///e%3A/Praktikum/API%20Anwendung/jss/init.js":{"language":"JavaScript","code":153,"comment":38,"blank":21},"file:///e%3A/Praktikum/API%20Anwendung/jss/backgroundELement.js":{"language":"JavaScript","code":69,"comment":21,"blank":10},"file:///e%3A/Praktikum/API%20Anwendung/jss/DomConstructor.js":{"language":"JavaScript","code":134,"comment":93,"blank":35},"file:///e%3A/Praktikum/API%20Anwendung/jss/utils.js":{"language":"JavaScript","code":26,"comment":4,"blank":4}}